cavapy.py
cavapy-0.4.0.dist-info/LICENSE
cavapy-0.4.0.dist-info/METADATA
cavapy-0.4.0.dist-info/WHEEL
cavapy-0.4.0.dist-info/RECORD
