Metadata-Version: 2.3
Name: cavapy
Version: 0.4.0
Summary: CAVA Python package. Retrive climate data.
License: MIT
Author: Riccardo Soldan
Author-email: riccardosoldan@hotmail.it
Requires-Python: >=3.11,<4.0
Classifier: License :: OSI Approved :: MIT License
Classifier: Operating System :: OS Independent
Classifier: Programming Language :: Python :: 3
Classifier: Programming Language :: Python :: 3.11
Classifier: Programming Language :: Python :: 3.12
Classifier: Programming Language :: Python :: 3.13
Requires-Dist: bottleneck
Requires-Dist: cartopy
Requires-Dist: dask
Requires-Dist: llvmlite
Requires-Dist: matplotlib
Requires-Dist: netcdf4
Requires-Dist: seaborn
Requires-Dist: xclim
Requires-Dist: xsdba
Project-URL: Repository, https://github.com/Risk-Team/cavapy
